Metadata-Version: 2.1
Name: odoo-addon-l10n_ch_adr_report
Version: 18.0.1.0.0.3
Requires-Python: >=3.10
Requires-Dist: odoo-addon-l10n_eu_product_adr_dangerous_goods==18.0.*
Requires-Dist: odoo==18.0.*
Summary: Print Delivery report to ADR swiss configuration
Home-page: https://github.com/OCA/l10n-switzerland
License: AGPL-3
Author: Camptocamp, Odoo Community Association (OCA)
Author-email: support@odoo-community.org
Classifier: Programming Language :: Python
Classifier: Framework :: Odoo
Classifier: Framework :: Odoo :: 18.0
Classifier: License :: OSI Approved :: GNU Affero General Public License v3
